hr.py
hr-0.1.dist-info/LICENSE
hr-0.1.dist-info/METADATA
hr-0.1.dist-info/WHEEL
hr-0.1.dist-info/entry_points.txt
hr-0.1.dist-info/top_level.txt
hr-0.1.dist-info/RECORD
