Metadata-Version: 2.1
Name: hr
Version: 0.1
Summary: Horizontal rule for your terminal
Home-page: http://github.com/euangoddard/hr.py
Author: Euan Goddard
License: UNKNOWN
Platform: UNKNOWN
License-File: LICENSE
